example_pkg/__init__.py
testfeng-0.1.0.dist-info/METADATA
testfeng-0.1.0.dist-info/RECORD
testfeng-0.1.0.dist-info/WHEEL
testfeng-0.1.0.dist-info/top_level.txt
