Metadata-Version: 2.1
Name: testfeng
Version: 0.1.0
Summary: get a chinesename by random
Home-page: https://github.com/mouday/chinesename
Author: fengxiaochuan
Author-email: fengxiaochuan@corp.netease.com
License: MIT License
Platform: UNKNOWN
